specviz/__init__.py
specviz/_astropy_init.py
specviz/app.py
specviz/conftest.py
specviz/version.py
specviz/core/__init__.py
specviz/core/hub.py
specviz/core/items.py
specviz/core/models.py
specviz/core/operations.py
specviz/core/plugin.py
specviz/data/linelists/Atomic-Ionic.list
specviz/data/linelists/Atomic-Ionic.yaml
specviz/data/linelists/CO.list
specviz/data/linelists/CO.yaml
specviz/data/linelists/Common_nebular.list
specviz/data/linelists/Common_nebular.yaml
specviz/data/linelists/Common_stellar.list
specviz/data/linelists/Common_stellar.yaml
specviz/data/linelists/H-He.list
specviz/data/linelists/H-He.yaml
specviz/data/linelists/H2.list
specviz/data/linelists/H2.yaml
specviz/data/linelists/Reader-Corliss.list
specviz/data/linelists/Reader-Corliss.yaml
specviz/data/linelists/SDSS-IV.list
specviz/data/linelists/SDSS-IV.yaml
specviz/data/linelists/SDSS.list
specviz/data/linelists/SDSS.yaml
specviz/data/linelists/illss.list
specviz/data/linelists/illss.yaml
specviz/data/linelists/tests/Common_stellar.list
specviz/data/linelists/tests/Common_stellar.yaml
specviz/data/resources/005-stats.svg
specviz/data/resources/006-invisible.svg
specviz/data/resources/007-visibility.png
specviz/data/resources/007-visibility.svg
specviz/data/resources/012-file.svg
specviz/data/resources/014-calculator.svg
specviz/data/resources/014-save.svg
specviz/data/resources/015-compass-1.svg
specviz/data/resources/015-new.svg
specviz/data/resources/048-line-chart.svg
specviz/data/resources/050-mask.svg
specviz/data/resources/CREDIT.md
specviz/data/resources/README.rst
specviz/data/resources/axis.svg
specviz/data/resources/color.svg
specviz/data/resources/configuration.svg
specviz/data/resources/crystal-ball.svg
specviz/data/resources/cube.svg
specviz/data/resources/delete-1.svg
specviz/data/resources/export.svg
specviz/data/resources/folder-2.svg
specviz/data/resources/folder.svg
specviz/data/resources/house.svg
specviz/data/resources/icon.png
specviz/data/resources/icon.svg
specviz-0.7.1.dist-info/METADATA
specviz-0.7.1.dist-info/WHEEL
specviz-0.7.1.dist-info/entry_points.txt
specviz-0.7.1.dist-info/top_level.txt
specviz-0.7.1.dist-info/RECORD
